nacwrap/__init__.py
nacwrap/_auth.py
nacwrap/_helpers.py
nacwrap/connections.py
nacwrap/data_model.py
nacwrap/datasources.py
nacwrap/exceptions.py
nacwrap/instances.py
nacwrap/tasks.py
nacwrap/users.py
nacwrap/workflows.py
nacwrap-0.3.4.dist-info/licenses/LICENSE
nacwrap-0.3.4.dist-info/METADATA
nacwrap-0.3.4.dist-info/WHEEL
nacwrap-0.3.4.dist-info/top_level.txt
nacwrap-0.3.4.dist-info/RECORD
