Metadata-Version: 2.4
Name: nacwrap
Version: 0.3.4
Summary: Python package that acts as a wrapper for the Nintex Automation Cloud system.
Home-page: https://github.com/pepsimidamerica/nacwrap
Author: Jordan Maynor
Author-email: jmaynor@pepsimidamerica.com
Classifier: Programming Language :: Python :: 3
Classifier: License :: OSI Approved :: The Unlicense (Unlicense)
Classifier: Operating System :: OS Independent
Requires-Python: >=3.10
License-File: LICENSE
Requires-Dist: requests
Requires-Dist: tenacity
Requires-Dist: pydantic
Requires-Dist: dotenv
Dynamic: author
Dynamic: author-email
Dynamic: classifier
Dynamic: description
Dynamic: description-content-type
Dynamic: home-page
Dynamic: license-file
Dynamic: requires-dist
Dynamic: requires-python
Dynamic: summary
